nr_wg_mtu_finder/__init__.py
nr_wg_mtu_finder/main.py
nr_wg_mtu_finder/main_heatmap.py
nr_wg_mtu_finder/mtu_finder.py
nr_wg_mtu_finder/plot.py
nr_wg_mtu_finder/sync_server.py
nr_wg_mtu_finder-0.2.1.dist-info/entry_points.txt
nr_wg_mtu_finder-0.2.1.dist-info/LICENSE
nr_wg_mtu_finder-0.2.1.dist-info/WHEEL
nr_wg_mtu_finder-0.2.1.dist-info/METADATA
nr_wg_mtu_finder-0.2.1.dist-info/RECORD
