Metadata-Version: 2.1
Name: nr-wg-mtu-finder
Version: 0.2.1
Summary: Scripts to find the optimal MTU for Wireguard server and peers.
Author: nitred
Author-email: nitish.k.reddy@gmail.com
Requires-Python: >=3.8
Classifier: Programming Language :: Python :: 3
Classifier: Programming Language :: Python :: 3.10
Classifier: Programming Language :: Python :: 3.8
Classifier: Programming Language :: Python :: 3.9
Requires-Dist: flask (==2.0.3)
Requires-Dist: matplotlib (==3.4.3)
Requires-Dist: pandas (==1.3.5)
Requires-Dist: pydantic (==1.8.2)
Requires-Dist: requests (==2.27.1)
Requires-Dist: seaborn (==0.11.2)
Requires-Dist: werkzeug (==2.0.3)
